CHANGES.rst
LICENSE.txt
MANIFEST.in
README.rst
requirements-extras.txt
setup.py
zabbix_client/__init__.py
zabbix_client/api_wrapper.py
zabbix_client/exceptions.py
zabbix_client.egg-info/PKG-INFO
zabbix_client.egg-info/SOURCES.txt
zabbix_client.egg-info/dependency_links.txt
zabbix_client.egg-info/requires.txt
zabbix_client.egg-info/top_level.txt