Metadata-Version: 1.1
Name: zabbix-client
Version: 0.1.2
Summary: Zabbix API wrapper
Home-page: https://github.com/jesuslosada/zabbix-client
Author: Jesús Losada Novo
Author-email: dev@jesuslosada.com
License: Apache 2.0
Keywords: zabbix,api,json-rpc,monitoring
Platform: UNKNOWN
Classifier: Development Status :: 4 - Beta
Classifier: Intended Audience :: Developers
Classifier: Intended Audience :: System Administrators
Classifier: License :: OSI Approved :: Apache Software License
Classifier: Natural Language :: English
Classifier: Operating System :: OS Independent
Classifier: Programming Language :: Python
Classifier: Programming Language :: Python :: 2
Classifier: Programming Language :: Python :: 3
Classifier: Topic :: Software Development :: Libraries
Classifier: Topic :: System :: Monitoring
Classifier: Topic :: System :: Networking :: Monitoring
Classifier: Topic :: System :: Systems Administration
